terminal_stopwatch/__init__.py
terminal_stopwatch/ascii_numbers.py
terminal_stopwatch/constants.py
terminal_stopwatch/input_handler.py
terminal_stopwatch/main.py
terminal_stopwatch/models.py
terminal_stopwatch/stopwatch.py
terminal_stopwatch/terminal.py
terminal_stopwatch-1.2.0.dist-info/LICENSE
terminal_stopwatch-1.2.0.dist-info/METADATA
terminal_stopwatch-1.2.0.dist-info/WHEEL
terminal_stopwatch-1.2.0.dist-info/entry_points.txt
terminal_stopwatch-1.2.0.dist-info/RECORD
