Metadata-Version: 2.1
Name: terminal-stopwatch
Version: 1.2.0
Summary: A terminal-based stopwatch application featuring ASCII art display
Home-page: https://www.taejun.lol
Keywords: stopwatch,terminal,ascii-art,timer
Author: taejun
Author-email: dugudugu0622@gmail.com
Requires-Python: >=3.11,<3.14
Classifier: Development Status :: 4 - Beta
Classifier: Environment :: Console
Classifier: Intended Audience :: End Users/Desktop
Classifier: License :: OSI Approved :: MIT License
Classifier: Operating System :: OS Independent
Classifier: Programming Language :: Python :: 3
Classifier: Programming Language :: Python :: 3.11
Classifier: Programming Language :: Python :: 3.12
Classifier: Topic :: Utilities
Requires-Dist: colorama (>=0.4.6,<0.5.0)
Requires-Dist: keyboard (>=0.13.5,<0.14.0)
Requires-Dist: pyinstaller (>=6.12.0,<7.0.0)
Requires-Dist: readchar (>=4.2.1,<5.0.0)
Project-URL: Repository, https://github.com/taejun0622/stopwatch
